hwffd/hwffd.py
hwffd/__init__.py
hwffd-0.1.dist-info/DESCRIPTION.rst
hwffd-0.1.dist-info/METADATA
hwffd-0.1.dist-info/metadata.json
hwffd-0.1.dist-info/RECORD
hwffd-0.1.dist-info/top_level.txt
hwffd-0.1.dist-info/WHEEL
