Metadata-Version: 2.0
Name: hwffd
Version: 0.1
Summary: Hello World From Francois Durand
Home-page: https://github.com/francois-durand/hwffd
Author: François Durand
Author-email: fradurand@gmail.com
License: BSD
Keywords: hwffd
Platform: UNKNOWN
Classifier: Development Status :: 2 - Pre-Alpha
Classifier: Intended Audience :: Developers
Classifier: License :: OSI Approved :: BSD License
Classifier: Natural Language :: English
Classifier: Programming Language :: Python :: 2
Classifier: Programming Language :: Python :: 2.6
Classifier: Programming Language :: Python :: 2.7
Classifier: Programming Language :: Python :: 3
Classifier: Programming Language :: Python :: 3.3
Classifier: Programming Language :: Python :: 3.4
